quick_xmltodict-0.1.3.dist-info/METADATA
quick_xmltodict-0.1.3.dist-info/WHEEL
quick_xmltodict-0.1.3.dist-info/licenses/LICENSE
quick_xmltodict/__init__.py
quick_xmltodict/__init__.pyi
quick_xmltodict/py.typed
quick_xmltodict/quick_xmltodict.cpython-311-powerpc64le-linux-gnu.so
quick_xmltodict-0.1.3.dist-info/RECORD
