Metadata-Version: 2.4
Name: quick-xmltodict
Version: 0.1.3
Classifier: Intended Audience :: Developers
Classifier: Programming Language :: Python :: Implementation :: CPython
Classifier: Programming Language :: Python :: Implementation :: PyPy
Classifier: Programming Language :: Python :: 3.10
Classifier: Programming Language :: Python :: 3.11
Classifier: Programming Language :: Python :: 3.12
Classifier: Programming Language :: Rust
Classifier: Topic :: Text Processing :: Markup :: XML
Classifier: Typing :: Typed
License-File: LICENSE
Summary: Efficient XML-to-dict conversion backed by Rust
Keywords: xmltodict,xml-to-dict,xml,fast,rust
Author-email: Daniel Hjertholm <8713259+danhje@users.noreply.github.com>
License: MIT
Requires-Python: >=3.10
Project-URL: Repository, https://github.com/statnett/quick-xmltodict
